[
    {
      "id": 100,
      "login": "smith@gmail.com",
      "orders": 312,
      "status": "Ценитель красоты"
    },
    {
      "id": 2,
      "login": "lenin@gmail.com",
      "orders": 120,
      "status": "Поставщик аксессуаров"
    },
    {
      "id": 3,
      "login": "mask@gmail.com",
      "orders": 98,
      "status": "Конкурент минздрава"
    },
    {
      "id": 4,
      "login": "dog@mail.ru",
      "orders": 674,
      "status": "рыбак"
    },
    {
      "id": 5,
      "login": "nightmare@mail.ru",
      "orders": 34,
      "status": "охотник"
    },
    {
      "id": 6,
      "login": "cat@mail.ru",
      "orders": 1,
      "status": "Ценитель красоты"
    }
  ]